wsgi_aws_unproxy.py
wsgi_aws_unproxy-1.2.1.dist-info/AUTHORS
wsgi_aws_unproxy-1.2.1.dist-info/LICENSE
wsgi_aws_unproxy-1.2.1.dist-info/METADATA
wsgi_aws_unproxy-1.2.1.dist-info/WHEEL
wsgi_aws_unproxy-1.2.1.dist-info/top_level.txt
wsgi_aws_unproxy-1.2.1.dist-info/RECORD
