Metadata-Version: 2.1
Name: wsgi-aws-unproxy
Version: 1.2.1
Summary: Simple wsgi middleware to unproxy AWS
Home-page: https://github.com/labd/wsgi-aws-unproxy
Author: Lab Digital
Author-email: opensource@labdigital.nl
License: MIT
Platform: UNKNOWN
Classifier: Development Status :: 5 - Production/Stable
Classifier: License :: OSI Approved :: MIT License
Classifier: Programming Language :: Python :: 2
Classifier: Programming Language :: Python :: 2.7
Classifier: Programming Language :: Python :: 3
Classifier: Programming Language :: Python :: 3.5
Classifier: Programming Language :: Python :: 3.6
Classifier: Programming Language :: Python :: 3.7
Classifier: Programming Language :: Python :: 3.8
Classifier: Programming Language :: Python :: Implementation :: CPython
Classifier: Programming Language :: Python :: Implementation :: PyPy
Requires-Dist: netaddr (>=0.7.19)
Requires-Dist: requests (>=2.23.0)
Provides-Extra: docs
Requires-Dist: sphinx (>=1.4.0) ; extra == 'docs'
Provides-Extra: test
Requires-Dist: coverage[toml] (==5.0.3) ; extra == 'test'
Requires-Dist: requests-mock (==1.3.0) ; extra == 'test'
Requires-Dist: pytest-cov (>=2.2.0) ; extra == 'test'
Requires-Dist: pytest (>=2.8.3) ; extra == 'test'
Requires-Dist: isort[pyproject] (==4.3.21) ; extra == 'test'
Requires-Dist: flake8 (==3.0.3) ; extra == 'test'
Requires-Dist: flake8-blind-except (==0.1.1) ; extra == 'test'
Requires-Dist: flake8-debugger (==1.4.0) ; extra == 'test'
Requires-Dist: flake8-imports ; extra == 'test'
